helix_fhir_client_sdk/__init__.py
helix_fhir_client_sdk/dictionary_parser.py
helix_fhir_client_sdk/dictionary_writer.py
helix_fhir_client_sdk/fhir_auth_mixin.py
helix_fhir_client_sdk/fhir_bundle_appender.py
helix_fhir_client_sdk/fhir_client.py
helix_fhir_client_sdk/fhir_delete_mixin.py
helix_fhir_client_sdk/fhir_merge_mixin.py
helix_fhir_client_sdk/fhir_merge_resources_mixin.py
helix_fhir_client_sdk/fhir_patch_mixin.py
helix_fhir_client_sdk/fhir_update_mixin.py
helix_fhir_client_sdk/function_types.py
helix_fhir_client_sdk/py.typed
helix_fhir_client_sdk/well_known_configuration.py
helix_fhir_client_sdk/exceptions/__init__.py
helix_fhir_client_sdk/exceptions/fhir_get_exception.py
helix_fhir_client_sdk/exceptions/fhir_sender_exception.py
helix_fhir_client_sdk/exceptions/fhir_validation_exception.py
helix_fhir_client_sdk/filters/__init__.py
helix_fhir_client_sdk/filters/base_filter.py
helix_fhir_client_sdk/filters/identifier_filter.py
helix_fhir_client_sdk/filters/last_updated_filter.py
helix_fhir_client_sdk/filters/property_filter.py
helix_fhir_client_sdk/filters/property_missing_filter.py
helix_fhir_client_sdk/filters/security_access_filter.py
helix_fhir_client_sdk/filters/security_owner_filter.py
helix_fhir_client_sdk/filters/sort_field.py
helix_fhir_client_sdk/filters/source_filter.py
helix_fhir_client_sdk/filters/version_filter.py
helix_fhir_client_sdk/graph/__init__.py
helix_fhir_client_sdk/graph/fhir_graph_mixin.py
helix_fhir_client_sdk/graph/graph_definition.py
helix_fhir_client_sdk/graph/graph_link_parameters.py
helix_fhir_client_sdk/graph/graph_target_parameters.py
helix_fhir_client_sdk/graph/simulated_graph_processor_mixin.py
helix_fhir_client_sdk/graph/test/__init__.py
helix_fhir_client_sdk/graph/test/test_graph_mixin.py
helix_fhir_client_sdk/graph/test/test_simulate_graph_processor_mixin.py
helix_fhir_client_sdk/graph/test/test_simulate_graph_processor_mixin_caching.py
helix_fhir_client_sdk/open_telemetry/__init__.py
helix_fhir_client_sdk-4.2.26.dist-info/licenses/LICENSE
helix_fhir_client_sdk-4.2.26.dist-info/METADATA
helix_fhir_client_sdk-4.2.26.dist-info/WHEEL
helix_fhir_client_sdk-4.2.26.dist-info/top_level.txt
helix_fhir_client_sdk-4.2.26.dist-info/RECORD
