Metadata-Version: 2.4
Name: helix.fhir.client.sdk
Version: 4.2.26
Summary: helix.fhir.client.sdk
Home-page: https://github.com/icanbwell/helix.fhir.client.sdk
Author: Imran Qureshi
Author-email: imran@icanbwell.com
Classifier: Development Status :: 4 - Beta
Classifier: Programming Language :: Python :: 3
Classifier: License :: OSI Approved :: Apache Software License
Classifier: Operating System :: OS Independent
Requires-Python: >=3.10
License-File: LICENSE
Requires-Dist: furl
Requires-Dist: requests
Requires-Dist: urllib3
Requires-Dist: chardet
Requires-Dist: aiohttp
Requires-Dist: async-timeout>=4.0.3
Requires-Dist: python-dateutil
Requires-Dist: compressedfhir<3,>=1.0.13
Requires-Dist: certifi>=2025.1.31
Requires-Dist: opentelemetry-api>=1.39
Requires-Dist: multidict>=6
Dynamic: author
Dynamic: author-email
Dynamic: classifier
Dynamic: description
Dynamic: description-content-type
Dynamic: home-page
Dynamic: license-file
Dynamic: requires-dist
Dynamic: requires-python
Dynamic: summary
